robopulser/__init__.py
robopulser/model_builder.py
robopulser/pulser.py
robopulser/robopulser.py
robopulser/scripts/__init__.py
robopulser/scripts/shell.py
robopulser/scripts/templates/example.yml
robopulser/scripts/templates/pulser.py
robopulser-0.2.2.dist-info/LICENSE
robopulser-0.2.2.dist-info/METADATA
robopulser-0.2.2.dist-info/WHEEL
robopulser-0.2.2.dist-info/entry_points.txt
robopulser-0.2.2.dist-info/RECORD
