Metadata-Version: 2.1
Name: robopulser
Version: 0.2.2
Summary: Simple package imitating heartbeat (using database timestamp updates)
License: MIT
Author: Wojciech Jankiewicz
Author-email: jankiwojciech@outlook.com
Requires-Python: >=3.10,<4.0
Classifier: License :: OSI Approved :: MIT License
Classifier: Programming Language :: Python :: 3
Classifier: Programming Language :: Python :: 3.10
Classifier: Programming Language :: Python :: 3.11
Classifier: Programming Language :: Python :: 3.12
Provides-Extra: mssql
Provides-Extra: mysql
Provides-Extra: poostgress
Provides-Extra: postgresss1
Requires-Dist: mysql-connector-python ; extra == "mysql"
Requires-Dist: pg8000 ; extra == "postgresss1"
Requires-Dist: psycopg2 ; extra == "poostgress"
Requires-Dist: pymssql ; extra == "mssql"
Requires-Dist: pyyaml
Requires-Dist: sqlalchemy
